kenobix/__init__.py
kenobix/backends/__init__.py
kenobix/backends/base.py
kenobix/backends/postgres.py
kenobix/backends/sqlite.py
kenobix/cli/__init__.py
kenobix/cli/dump.py
kenobix/cli/export.py
kenobix/cli/import_cmd.py
kenobix/cli/info.py
kenobix/cli/migrate.py
kenobix/cli/parser.py
kenobix/cli/schema.py
kenobix/cli/serve.py
kenobix/cli/utils.py
kenobix/collection.py
kenobix/fields.py
kenobix/kenobix.py
kenobix/migrate.py
kenobix/odm.py
kenobix/webui/__init__.py
kenobix/webui/api.py
kenobix/webui/app.py
kenobix/webui/config.py
kenobix/webui/db_helpers.py
kenobix/webui/formatters.py
kenobix/webui/pagination.py
kenobix/webui/routes.py
kenobix/webui/schema.py
kenobix/webui/search.py
kenobix/webui/server.py
kenobix/webui/state.py
kenobix/webui/templates/base.html
kenobix/webui/templates/collection.html
kenobix/webui/templates/document.html
kenobix/webui/templates/error.html
kenobix/webui/templates/index.html
kenobix/webui/templates/search.html
kenobix-0.11.1.dist-info/WHEEL
kenobix-0.11.1.dist-info/entry_points.txt
kenobix-0.11.1.dist-info/METADATA
kenobix-0.11.1.dist-info/RECORD
