Metadata-Version: 2.3
Name: kenobix
Version: 0.11.1
Summary: High-performance document database with SQLite and PostgreSQL backends, based on KenobiDB by Harrison Erd.
Author: Harrison Erd, Stefane Fermigier
Author-email: Harrison Erd <harrisonerd@gmail.com>, Stefane Fermigier <sf@fermigier.com>
License: Copyright 2024-2025 Harrison Erd
Classifier: Environment :: Console
Classifier: Development Status :: 4 - Beta
Classifier: Programming Language :: Python :: 3
Classifier: Programming Language :: Python :: 3.11
Classifier: Programming Language :: Python :: 3.12
Classifier: Programming Language :: Python :: 3.13
Classifier: Programming Language :: Python :: 3.14
Classifier: License :: OSI Approved :: BSD License
Classifier: Intended Audience :: Developers
Classifier: Topic :: Database
Classifier: Topic :: Database :: Database Engines/Servers
Classifier: Topic :: Software Development :: Libraries :: Python Modules
Requires-Dist: cattrs>=25.3.0
Requires-Dist: psycopg2-binary>=2.9 ; extra == 'all'
Requires-Dist: bottle>=0.13 ; extra == 'all'
Requires-Dist: jinja2>=3.1 ; extra == 'all'
Requires-Dist: psycopg2-binary>=2.9 ; extra == 'postgres'
Requires-Dist: bottle>=0.13 ; extra == 'webui'
Requires-Dist: jinja2>=3.1 ; extra == 'webui'
Maintainer: KenobiX Contributors
Requires-Python: >=3.11
Project-URL: Homepage, https://github.com/abilian/kenobix
Project-URL: Issue Tracker, https://github.com/abilian/kenobix/issues
Project-URL: Original Project, https://github.com/patx/kenobi
Project-URL: Source Code, https://github.com/abilian/kenobix
Provides-Extra: all
Provides-Extra: postgres
Provides-Extra: webui
